yud102023/goodbye.py
yud102023/init.py
yud102023-0.1.1.dist-info/LICENSE
yud102023-0.1.1.dist-info/METADATA
yud102023-0.1.1.dist-info/WHEEL
yud102023-0.1.1.dist-info/top_level.txt
yud102023-0.1.1.dist-info/RECORD
