Metadata-Version: 2.1
Name: yud102023
Version: 0.1.1
Summary: A small creactive goodbye project for my students
Author-email: Tomereliel <tomereliel.dev@gmail.com>
Project-URL: Homepage, https://github.com/pypa/sampleproject
Project-URL: Bug Tracker, https://github.com/pypa/sampleproject/issues
Classifier: Programming Language :: Python :: 3
Classifier: License :: OSI Approved :: MIT License
Classifier: Operating System :: OS Independent
Requires-Python: >=3.7
License-File: LICENSE
Requires-Dist: keyboard
